sequana_pipelines/mapper/__init__.py
sequana_pipelines/mapper/config.yaml
sequana_pipelines/mapper/dag.png
sequana_pipelines/mapper/logo.png
sequana_pipelines/mapper/main.py
sequana_pipelines/mapper/mapper.rules
sequana_pipelines/mapper/multiqc_config.yaml
sequana_pipelines/mapper/schema.yaml
sequana_pipelines/mapper/tools.txt
sequana_mapper-1.3.1.dist-info/LICENSE
sequana_mapper-1.3.1.dist-info/METADATA
sequana_mapper-1.3.1.dist-info/WHEEL
sequana_mapper-1.3.1.dist-info/entry_points.txt
sequana_mapper-1.3.1.dist-info/RECORD
