Metadata-Version: 2.1
Name: sequana-mapper
Version: 1.3.1
Summary: A multi-sample mapper to map reads onto a reference
Home-page: https://github.com/sequana/mapper
License: BSD-3
Keywords: snakemake,NGS,sequana,bwa,minimap2
Author: Sequana Team
Requires-Python: >=3.9,<4.0
Classifier: Development Status :: 5 - Production/Stable
Classifier: Intended Audience :: Developers
Classifier: Intended Audience :: Education
Classifier: Intended Audience :: End Users/Desktop
Classifier: Intended Audience :: Science/Research
Classifier: License :: OSI Approved :: BSD License
Classifier: License :: Other/Proprietary License
Classifier: Operating System :: POSIX :: Linux
Classifier: Programming Language :: Python :: 3
Classifier: Programming Language :: Python :: 3.9
Classifier: Programming Language :: Python :: 3.10
Classifier: Programming Language :: Python :: 3.11
Classifier: Programming Language :: Python :: 3.12
Classifier: Programming Language :: Python :: 3.13
Classifier: Topic :: Scientific/Engineering :: Bio-Informatics
Classifier: Topic :: Scientific/Engineering :: Information Analysis
Classifier: Topic :: Software Development :: Libraries :: Python Modules
Requires-Dist: click-completion (>=0.5.2,<0.6.0)
Requires-Dist: sequana (>=0.18.0)
Requires-Dist: sequana_pipetools (>=1.1.1)
Project-URL: Repository, https://github.com/sequana/mapper
